./LICENSE
./MANIFEST.in
./PKG-INFO
./README.md
./config.py
./mcp_server_stable.py
./msf_advanced_session_manager.py
./msf_advanced_tools.py
./msf_ecosystem_tools.py
./msf_enhanced_tools.py
./msf_extended_tools.py
./msf_final_five_tools.py
./msf_plugin_system.py
./msf_stable_integration.py
./package_name
./pyproject.toml
./requirements.txt
./safe_context.py
./iflow_mcp_lyftium_inc_msfconsole_mcp-5.0.5/LICENSE
./iflow_mcp_lyftium_inc_msfconsole_mcp-5.0.5/PKG-INFO
./iflow_mcp_lyftium_inc_msfconsole_mcp-5.0.5/README.md
./iflow_mcp_lyftium_inc_msfconsole_mcp-5.0.5/config.py
./iflow_mcp_lyftium_inc_msfconsole_mcp-5.0.5/mcp_server_stable.py
./iflow_mcp_lyftium_inc_msfconsole_mcp-5.0.5/msf_advanced_session_manager.py
./iflow_mcp_lyftium_inc_msfconsole_mcp-5.0.5/msf_advanced_tools.py
./iflow_mcp_lyftium_inc_msfconsole_mcp-5.0.5/msf_enhanced_tools.py
./iflow_mcp_lyftium_inc_msfconsole_mcp-5.0.5/msf_extended_tools.py
./iflow_mcp_lyftium_inc_msfconsole_mcp-5.0.5/msf_plugin_system.py
./iflow_mcp_lyftium_inc_msfconsole_mcp-5.0.5/msf_stable_integration.py
./iflow_mcp_lyftium_inc_msfconsole_mcp-5.0.5/package_name
./iflow_mcp_lyftium_inc_msfconsole_mcp-5.0.5/pyproject.toml
./iflow_mcp_lyftium_inc_msfconsole_mcp-5.0.5/requirements.txt
./iflow_mcp_lyftium_inc_msfconsole_mcp-5.0.5/safe_context.py
./iflow_mcp_lyftium_inc_msfconsole_mcp-5.0.5/plugins/auto_add_route_plugin.py
./iflow_mcp_lyftium_inc_msfconsole_mcp-5.0.5/plugins/nessus_plugin.py
./iflow_mcp_lyftium_inc_msfconsole_mcp-5.0.5/plugins/session_notifier_plugin.py
./iflow_mcp_lyftium_inc_msfconsole_mcp-5.0.5/plugins/token_hunter_plugin.py
./iflow_mcp_lyftium_inc_msfconsole_mcp-5.0.5/plugins/wmap_plugin.py
./plugins/auto_add_route_plugin.py
./plugins/nessus_plugin.py
./plugins/session_notifier_plugin.py
./plugins/token_hunter_plugin.py
./plugins/wmap_plugin.py
iflow_mcp_lyftium_inc_msfconsole_mcp-5.1.2.dist-info/METADATA
iflow_mcp_lyftium_inc_msfconsole_mcp-5.1.2.dist-info/WHEEL
iflow_mcp_lyftium_inc_msfconsole_mcp-5.1.2.dist-info/licenses/LICENSE
iflow_mcp_lyftium_inc_msfconsole_mcp-5.1.2.dist-info/RECORD
