Metadata-Version: 2.4
Name: iflow-mcp_lyftium-inc-msfconsole-mcp
Version: 5.1.2
Summary: Complete MSF ecosystem MCP server with 95%+ coverage (58 tools)
Project-URL: Homepage, https://github.com/LYFTIUM-INC/msfconsole-mcp
Project-URL: Repository, https://github.com/LYFTIUM-INC/msfconsole-mcp
Project-URL: Issues, https://github.com/LYFTIUM-INC/msfconsole-mcp/issues
Author-email: LYFTIUM-INC <support@iflow.com>
License: MIT
License-File: LICENSE
Classifier: Development Status :: 5 - Production/Stable
Classifier: Intended Audience :: Developers
Classifier: License :: OSI Approved :: MIT License
Classifier: Programming Language :: Python :: 3
Classifier: Programming Language :: Python :: 3.8
Classifier: Programming Language :: Python :: 3.9
Classifier: Programming Language :: Python :: 3.10
Classifier: Programming Language :: Python :: 3.11
Classifier: Programming Language :: Python :: 3.12
Requires-Python: >=3.8
Requires-Dist: mcp>=1.0.0
Requires-Dist: psutil>=5.9.0
